emerald/__init__.py
emerald/boa/__init__.py
emerald/boa/_base.py
emerald/boa/_classification.py
emerald/boa/_regression.py
emerald/boa/_tree.py
emerald/gems/__init__.py
emerald/gems/_data.py
emerald/optimal_models/__init__.py
emerald/optimal_models/_classifiers.py
emerald/optimal_models/_regressors.py
emeraldml-0.0.1.dist-info/LICENSE
emeraldml-0.0.1.dist-info/METADATA
emeraldml-0.0.1.dist-info/WHEEL
emeraldml-0.0.1.dist-info/top_level.txt
emeraldml-0.0.1.dist-info/RECORD
