Metadata-Version: 2.1
Name: emeraldml
Version: 0.0.1
Summary: Accelerating machine learning during the exploratory phase
Home-page: https://github.com/yu3ufff/emerald
Author: Yusuf Abdulla
Author-email: yusuf.m.abdulla@gmail.com
License: UNKNOWN
Platform: UNKNOWN
Classifier: Programming Language :: Python :: 3
Classifier: License :: OSI Approved :: MIT License
Classifier: Operating System :: OS Independent
Requires-Python: >=3.7
License-File: LICENSE
